or_testbed/__init__.py
or_testbed/entities/__init__.py
or_testbed/entities/candidate.py
or_testbed/entities/instance.py
or_testbed/entities/move.py
or_testbed/entities/neighborhood.py
or_testbed/entities/solution.py
or_testbed/solvers/__init__.py
or_testbed/solvers/factory.py
or_testbed/solvers/base/__init__.py
or_testbed/solvers/base/move.py
or_testbed/solvers/base/solver.py
or_testbed/solvers/grasp/__init__.py
or_testbed/solvers/grasp/construct.py
or_testbed/solvers/simanneal/__init__.py
or_testbed/solvers/simanneal/exceptions.py
or_testbed/solvers/simanneal/multistart.py
or_testbed/solvers/simanneal/simanneal.py
or_testbed/solvers/tabusearch/__init__.py
or_testbed/solvers/tabusearch/multistart.py
or_testbed/solvers/tabusearch/tabu.py
or_testbed/solvers/tabusearch/tabulist.py
or_testbed/utils/__init__.py
or_testbed/utils/logger.py
or_testbed-1.0.2.dist-info/LICENSE
or_testbed-1.0.2.dist-info/METADATA
or_testbed-1.0.2.dist-info/WHEEL
or_testbed-1.0.2.dist-info/top_level.txt
or_testbed-1.0.2.dist-info/RECORD
