Metadata-Version: 2.1
Name: or-testbed
Version: 1.0.2
Summary: Operations Research Framework for building metaheuristic algorithms.
Home-page: https://github.com/Fynardo/or-testbed
Author: Diego Noceda
Author-email: dfynar@gmail.com
License: UNKNOWN
Platform: UNKNOWN
Classifier: Programming Language :: Python :: 3
Classifier: License :: OSI Approved :: MIT License
Classifier: Operating System :: OS Independent
Requires-Python: >=3.5
